vfb_connect/__init__.py
vfb_connect/_fallback_version.py
vfb_connect/_version.py
vfb_connect/cross_server_tools.py
vfb_connect/default_servers.py
vfb_connect/lookup_cache.pkl
vfb_connect/neo/__init__.py
vfb_connect/neo/neo4j_tools.py
vfb_connect/neo/query_wrapper.py
vfb_connect/neo/test/__init__.py
vfb_connect/neo/test/neo_tools_test.py
vfb_connect/neo/test/resources/fbbt-simple.json
vfb_connect/neo/test/resources/so.json
vfb_connect/neo/test/resources/vfb_ext.json
vfb_connect/owl/__init__.py
vfb_connect/owl/owlery_query_tools.py
vfb_connect/owl/test/__init__.py
vfb_connect/owl/test/query_tools_test.py
vfb_connect/resources/VFB_TermInfo_queries.json
vfb_connect/resources/VFB_results_multi_input.json
vfb_connect/resources/VFB_results_single_input.json
vfb_connect/schema/__init__.py
vfb_connect/schema/vfb_term.py
vfb_connect/schema/test/__init__.py
vfb_connect/schema/test/vfb_term_query_test.py
vfb_connect/schema/test/vfb_term_test.py
vfb_connect/test/__init__.py
vfb_connect/test/cross_server_tools_test.py
vfb_connect-2.3.9.dist-info/LICENSE
vfb_connect-2.3.9.dist-info/METADATA
vfb_connect-2.3.9.dist-info/WHEEL
vfb_connect-2.3.9.dist-info/top_level.txt
vfb_connect-2.3.9.dist-info/RECORD
