Metadata-Version: 2.1
Name: vfb-connect
Version: 2.3.9
Summary: Wrapper for querying VirtualFlyBrain servers.
Author-email: Robert Court <rcourt@ed.ac.uk>
License: GPL-3.0-or-later
Project-URL: Homepage, https://github.com/VirtualFlyBrain/VFB_connect
Project-URL: Documentation, https://vfb-connect.readthedocs.io/en/stable/
Project-URL: Repository, https://github.com/VirtualFlyBrain/VFB_connect
Project-URL: Bug Reports, https://github.com/VirtualFlyBrain/VFB_connect/issues
Classifier: Development Status :: 5 - Production/Stable
Classifier: Intended Audience :: Science/Research
Classifier: Programming Language :: Python :: 3
Classifier: Programming Language :: Python :: 3.8
Classifier: Programming Language :: Python :: 3.9
Classifier: Programming Language :: Python :: 3.10
Classifier: Programming Language :: Python :: 3.11
Classifier: Programming Language :: Python :: 3.12
Requires-Python: >=3.8
License-File: LICENSE
Requires-Dist: requests
Requires-Dist: pandas
Requires-Dist: jsonpath-rw
Requires-Dist: pysolr
Requires-Dist: navis
Requires-Dist: numpy<2.0.0,>=1.26.4
Requires-Dist: seaborn>0.13
Requires-Dist: colormath
Requires-Dist: tqdm
